menu/__init__.py
menu/combo/__init__.py
menu/combo/dietcombo.py
menu/combo/regularcombo.py
menu/combo/testdietcombo.py
menu/combo/testregcombo.py
menu/freeorder/Test_Kid.py
menu/freeorder/Test_Regular.py
menu/freeorder/__init__.py
menu/freeorder/kidsmeal.py
menu/freeorder/regularorder.py
menupkg-0.1.dist-info/LICENSE.txt
menupkg-0.1.dist-info/METADATA
menupkg-0.1.dist-info/WHEEL
menupkg-0.1.dist-info/top_level.txt
menupkg-0.1.dist-info/RECORD
