Metadata-Version: 2.1
Name: menupkg
Version: 0.1
Summary: A test python package
Home-page: https://github.com/ubco-mds-2020-labs/data-533-lab-4-monajmn
Author: F. Liu, M. Jia
Author-email: liufengcheng_barry@outlook.com
License: MIT
Platform: UNKNOWN
Requires-Dist: tabulate
